{
  "sources": {
    "abc1": {
      "id": "abc1",
      "name": "ABC News",
      "home_url": "https://abcnews.com/",
      "kind": "hero",
      "created_at": "2026-03-01T22:32:46.825Z",
      "updated_at": "2026-03-01T22:32:58.538Z",
      "ok": true,
      "stale": false,
      "item": {
        "title": "Iran live updates: Trump says there will 'likely' be more US casualties",
        "url": "https://abcnews.com/International/live-updates/iran-live-updates-israel-launches-preemptive-strike-iran?id=130301492",
        "imgUrl": null,
        "contentType": "live",
        "breakingLabel": null,
        "breakingHeadline": null,
        "breakingUrl": null,
        "slotKey": "5be6806db8a5"
      },
      "last": {
        "runId": "abc_2026-03-01T22-32-50-685Z",
        "ok": true,
        "error": null,
        "fetchedAt": "2026-03-01T22:32:58.538Z",
        "shot": {
          "object_path": "screenshots/abc1/2026/03/01/abc_2026-03-01T22-32-50-685Z.jpg",
          "shot_url": null
        }
      },
      "history": [],
      "archive": [
        {
          "runId": "abc_2026-03-01T22-32-50-685Z",
          "html": "/archive/abc_2026-03-01T22-32-50-685Z.html",
          "json": "/archive/abc_2026-03-01T22-32-50-685Z.json"
        }
      ]
    },
    "cbs1": {
      "id": "cbs1",
      "name": "CBS News",
      "home_url": "https://www.cbsnews.com/",
      "kind": "hero",
      "created_at": "2026-03-01T22:32:46.825Z",
      "updated_at": "2026-03-01T22:33:04.940Z",
      "ok": true,
      "stale": false,
      "item": {
        "title": "Trump says Iran operation could take \"four weeks or less,\" 3 U.S. troops killed",
        "url": "https://cbsnews.com/live-updates/us-iran-war-israel-supreme-leader-khamenei-funeral-day-2",
        "imgUrl": null,
        "slotKey": "4d6f70f0b663",
        "contentType": "live"
      },
      "last": {
        "runId": "cbs_2026-03-01T22-32-59-300Z",
        "ok": true,
        "error": null,
        "fetchedAt": "2026-03-01T22:33:04.940Z",
        "shot": {
          "object_path": "screenshots/cbs1/2026/03/01/cbs_2026-03-01T22-32-59-300Z.jpg",
          "shot_url": null
        }
      },
      "history": [],
      "archive": [
        {
          "runId": "cbs_2026-03-01T22-32-59-300Z",
          "html": "/archive/cbs_2026-03-01T22-32-59-300Z.html",
          "json": "/archive/cbs_2026-03-01T22-32-59-300Z.json"
        }
      ]
    },
    "usat1": {
      "id": "usat1",
      "name": "USA Today",
      "home_url": "https://www.usatoday.com/",
      "kind": "hero",
      "created_at": "2026-03-01T22:32:46.825Z",
      "updated_at": "2026-03-01T22:33:09.859Z",
      "ok": true,
      "stale": false,
      "item": {
        "title": "Do Americans support Iran strikes? What the polling says",
        "url": "https://usatoday.com/story/news/politics/2026/03/01/iran-attack-trump-poll/88933730007",
        "imgUrl": "https://usatoday.com/gcdn/authoring/authoring-images/2026/02/28/USAT/88921860007-20260228-t-201808-z-718805311-rc-27-vjaee-6-hd-rtrmadp-3-irancrisisusa.JPG?auto=webp&crop=5615%2C3159%2Cx0%2Cy292&format=pjpg&height=242&width=430",
        "imgAlt": null,
        "dek": "A new Reuters/Ipsos poll finds low levels of support for the U.S.-Israel strikes on Iran that killed the country's supreme leader.",
        "breakingLabel": null,
        "breakingHeadline": null,
        "breakingUrl": null,
        "slotKey": "2f4f5e88af94",
        "contentType": "news"
      },
      "last": {
        "runId": "usat1_2026-03-01T22-33-05-607Z",
        "ok": true,
        "error": null,
        "fetchedAt": "2026-03-01T22:33:09.859Z",
        "shot": {
          "object_path": "screenshots/usat1/2026/03/01/usat1_2026-03-01T22-33-05-607Z.jpg",
          "shot_url": null
        }
      },
      "history": [],
      "archive": [
        {
          "runId": "usat1_2026-03-01T22-33-05-607Z",
          "html": "/archive/usat1_2026-03-01T22-33-05-607Z.html",
          "json": "/archive/usat1_2026-03-01T22-33-05-607Z.json"
        }
      ]
    },
    "nbc1": {
      "id": "nbc1",
      "name": "NBC News",
      "home_url": "https://www.nbcnews.com/",
      "kind": "hero",
      "created_at": "2026-03-01T22:32:46.825Z",
      "updated_at": "2026-03-01T22:33:16.331Z",
      "ok": true,
      "stale": false,
      "item": {
        "title": "Iran targets U.S. military assets",
        "url": "https://nbcnews.com/world/iran/live-blog/iran-attack-strikes-us-israel-trump-khamenei-dead-live-updates-rcna261172",
        "imgUrl": null,
        "slotKey": "579270cafa55",
        "contentType": "live"
      },
      "last": {
        "runId": "nbc_2026-03-01T22-33-10-588Z",
        "ok": true,
        "error": null,
        "fetchedAt": "2026-03-01T22:33:16.331Z",
        "shot": {
          "object_path": "screenshots/nbc1/2026/03/01/nbc_2026-03-01T22-33-10-588Z.jpg",
          "shot_url": null
        }
      },
      "history": [],
      "archive": [
        {
          "runId": "nbc_2026-03-01T22-33-10-588Z",
          "html": "/archive/nbc_2026-03-01T22-33-10-588Z.html",
          "json": "/archive/nbc_2026-03-01T22-33-10-588Z.json"
        }
      ]
    },
    "cnn1": {
      "id": "cnn1",
      "name": "CNN",
      "home_url": "https://www.cnn.com/",
      "kind": "hero",
      "created_at": "2026-03-01T22:32:46.825Z",
      "updated_at": "2026-03-01T22:33:24.505Z",
      "ok": true,
      "stale": false,
      "item": {
        "title": "Bleacher Report",
        "url": "https://bleacherreport.com/",
        "imgUrl": null,
        "slotKey": "e75971db9693",
        "contentType": "news"
      },
      "last": {
        "runId": "cnn1_2026-03-01T22-33-16-972Z",
        "ok": true,
        "error": null,
        "fetchedAt": "2026-03-01T22:33:24.505Z",
        "shot": {
          "object_path": "screenshots/cnn1/2026/03/01/cnn1_2026-03-01T22-33-16-972Z.jpg",
          "shot_url": null
        }
      },
      "history": [],
      "archive": [
        {
          "runId": "cnn1_2026-03-01T22-33-16-972Z",
          "html": "/archive/cnn1_2026-03-01T22-33-16-972Z.html",
          "json": "/archive/cnn1_2026-03-01T22-33-16-972Z.json"
        }
      ]
    },
    "guardian1": {
      "id": "guardian1",
      "name": "The Guardian",
      "home_url": "https://www.theguardian.com/",
      "kind": "hero",
      "created_at": "2026-03-01T22:32:46.825Z",
      "updated_at": "2026-03-01T22:33:29.274Z",
      "ok": true,
      "stale": false,
      "item": {
        "title": "Trump says attack on Iran ‘will continue until all of our objectives are achieved’",
        "url": "https://theguardian.com/us-news/live/2026/mar/01/us-israel-war-on-iran-ayatollah-ali-khamenei-i-dead-latest-reports",
        "imgUrl": null,
        "slotKey": "b80da2377db9",
        "contentType": "live"
      },
      "last": {
        "runId": "guardian1_2026-03-01T22-33-25-132Z",
        "ok": true,
        "error": null,
        "fetchedAt": "2026-03-01T22:33:29.274Z",
        "shot": {
          "object_path": "screenshots/guardian1/2026/03/01/guardian1_2026-03-01T22-33-25-132Z.jpg",
          "shot_url": null
        }
      },
      "history": [],
      "archive": [
        {
          "runId": "guardian1_2026-03-01T22-33-25-132Z",
          "html": "/archive/guardian1_2026-03-01T22-33-25-132Z.html",
          "json": "/archive/guardian1_2026-03-01T22-33-25-132Z.json"
        }
      ]
    },
    "ap1": {
      "id": "ap1",
      "name": "Associated Press",
      "home_url": "https://apnews.com/",
      "kind": "hero",
      "created_at": "2026-03-01T22:32:46.825Z",
      "updated_at": "2026-03-01T22:33:39.751Z",
      "ok": true,
      "stale": false,
      "item": {
        "title": "Trump says ‘there will likely be more’ US service members killed in Iran before conflict ends",
        "url": "https://apnews.com/live/us-israel-strikes-iran-khamenei-03-01-2026",
        "imgUrl": null,
        "slotKey": "083847305a8b",
        "contentType": "live"
      },
      "last": {
        "runId": "ap1_2026-03-01T22-33-29-853Z",
        "ok": true,
        "error": null,
        "fetchedAt": "2026-03-01T22:33:39.751Z",
        "shot": {
          "object_path": "screenshots/ap1/2026/03/01/ap1_2026-03-01T22-33-29-853Z.jpg",
          "shot_url": null
        }
      },
      "history": [],
      "archive": [
        {
          "runId": "ap1_2026-03-01T22-33-29-853Z",
          "html": "/archive/ap1_2026-03-01T22-33-29-853Z.html",
          "json": "/archive/ap1_2026-03-01T22-33-29-853Z.json"
        }
      ]
    },
    "latimes1": {
      "id": "latimes1",
      "name": "Los Angeles Times",
      "home_url": "https://www.latimes.com/",
      "kind": "hero",
      "created_at": "2026-03-01T22:32:46.825Z",
      "updated_at": "2026-03-01T22:33:47.505Z",
      "ok": true,
      "stale": false,
      "item": {
        "title": "Trump justifies Iran attack as Democrats raise doubt",
        "url": "https://latimes.com/world-nation/live/u-s-and-israel-attack-iran-tehran-retaliates",
        "imgUrl": null,
        "slotKey": "06617b56ef8d",
        "contentType": "live"
      },
      "last": {
        "runId": "latimes1_2026-03-01T22-33-40-507Z",
        "ok": true,
        "error": null,
        "fetchedAt": "2026-03-01T22:33:47.505Z",
        "shot": {
          "object_path": "screenshots/latimes1/2026/03/01/latimes1_2026-03-01T22-33-40-507Z.jpg",
          "shot_url": null
        }
      },
      "history": [],
      "archive": [
        {
          "runId": "latimes1_2026-03-01T22-33-40-507Z",
          "html": "/archive/latimes1_2026-03-01T22-33-40-507Z.html",
          "json": "/archive/latimes1_2026-03-01T22-33-40-507Z.json"
        }
      ]
    },
    "npr1": {
      "id": "npr1",
      "name": "NPR",
      "home_url": "https://www.npr.org/",
      "kind": "hero",
      "created_at": "2026-03-01T22:32:46.825Z",
      "updated_at": "2026-03-01T22:33:58.240Z",
      "ok": true,
      "stale": false,
      "item": {
        "title": "3 American soldiers killed as U.S.-Israeli war against Iran continues into 2nd day",
        "url": "https://npr.org/2026/03/01/nx-s1-5731365/us-israeli-strikes-region",
        "imgUrl": null,
        "slotKey": "3f6d722bf103",
        "contentType": "news"
      },
      "last": {
        "runId": "npr1_2026-03-01T22-33-48-057Z",
        "ok": true,
        "error": null,
        "fetchedAt": "2026-03-01T22:33:58.240Z",
        "shot": {
          "object_path": "screenshots/npr1/2026/03/01/npr1_2026-03-01T22-33-48-057Z.jpg",
          "shot_url": null
        }
      },
      "history": [],
      "archive": [
        {
          "runId": "npr1_2026-03-01T22-33-48-057Z",
          "html": "/archive/npr1_2026-03-01T22-33-48-057Z.html",
          "json": "/archive/npr1_2026-03-01T22-33-48-057Z.json"
        }
      ]
    },
    "bbc1": {
      "id": "bbc1",
      "name": "BBC",
      "home_url": "https://www.bbc.com/",
      "kind": "hero",
      "created_at": "2026-03-01T22:32:46.825Z",
      "updated_at": "2026-03-01T22:34:04.224Z",
      "ok": true,
      "stale": false,
      "item": {
        "title": "Iran operations 'ahead of schedule', says Trump as Tehran hits back across region",
        "url": "https://bbc.com/news/live/cn5ge95q6y7t",
        "imgUrl": null,
        "slotKey": "b890b46a9e6c",
        "contentType": "live"
      },
      "last": {
        "runId": "bbc1_2026-03-01T22-33-58-849Z",
        "ok": true,
        "error": null,
        "fetchedAt": "2026-03-01T22:34:04.224Z",
        "shot": {
          "object_path": "screenshots/bbc1/2026/03/01/bbc1_2026-03-01T22-33-58-849Z.jpg",
          "shot_url": null
        }
      },
      "history": [],
      "archive": [
        {
          "runId": "bbc1_2026-03-01T22-33-58-849Z",
          "html": "/archive/bbc1_2026-03-01T22-33-58-849Z.html",
          "json": "/archive/bbc1_2026-03-01T22-33-58-849Z.json"
        }
      ]
    },
    "fox1": {
      "id": "fox1",
      "name": "Fox News",
      "home_url": "https://www.foxnews.com/",
      "kind": "hero",
      "created_at": "2026-03-01T22:32:46.825Z",
      "updated_at": "2026-03-01T22:34:11.329Z",
      "ok": true,
      "stale": false,
      "item": {
        "title": "Trump vows 'most punishing blow to terrorists' after US service members killed in Iran operation",
        "url": "https://foxnews.com/politics/trump-pledges-avenge-fallen-us-service-members-tensions-iran-intensify",
        "imgUrl": null,
        "slotKey": "6b38efbc88f8",
        "contentType": "news"
      },
      "last": {
        "runId": "fox1_2026-03-01T22-34-04-747Z",
        "ok": true,
        "error": null,
        "fetchedAt": "2026-03-01T22:34:11.329Z",
        "shot": {
          "object_path": "screenshots/fox1/2026/03/01/fox1_2026-03-01T22-34-04-747Z.jpg",
          "shot_url": null
        }
      },
      "history": [],
      "archive": [
        {
          "runId": "fox1_2026-03-01T22-34-04-747Z",
          "html": "/archive/fox1_2026-03-01T22-34-04-747Z.html",
          "json": "/archive/fox1_2026-03-01T22-34-04-747Z.json"
        }
      ]
    },
    "yahoo1": {
      "id": "yahoo1",
      "name": "Yahoo News",
      "home_url": "https://news.yahoo.com/",
      "kind": "hero",
      "created_at": "2026-03-01T22:32:46.825Z",
      "updated_at": "2026-03-01T22:34:20.698Z",
      "ok": true,
      "stale": false,
      "item": {
        "title": "Trump says Iran leadership agrees to talks: 'They should have done it sooner'",
        "url": "https://news.yahoo.com/articles/trump-says-iran-leadership-agrees-183243728.html",
        "imgUrl": null,
        "slotKey": "c41bbb14e91d",
        "contentType": "news"
      },
      "last": {
        "runId": "yahoo1_2026-03-01T22-34-12-020Z",
        "ok": true,
        "error": null,
        "fetchedAt": "2026-03-01T22:34:20.698Z",
        "shot": {
          "object_path": "screenshots/yahoo1/2026/03/01/yahoo1_2026-03-01T22-34-12-020Z.jpg",
          "shot_url": null
        }
      },
      "history": [],
      "archive": [
        {
          "runId": "yahoo1_2026-03-01T22-34-12-020Z",
          "html": "/archive/yahoo1_2026-03-01T22-34-12-020Z.html",
          "json": "/archive/yahoo1_2026-03-01T22-34-12-020Z.json"
        }
      ]
    }
  }
}