{
  "sources": {
    "abc1": {
      "id": "abc1",
      "name": "ABC News",
      "home_url": "https://abcnews.com/",
      "kind": "hero",
      "created_at": "2026-03-28T19:03:14.326Z",
      "updated_at": "2026-03-28T19:03:25.337Z",
      "ok": true,
      "stale": false,
      "item": {
        "title": "'No Kings' protesters rally in cities, towns across the country",
        "url": "https://abcnews.com/Politics/kings-protesters-set-rally-cities-towns-country-saturday/story?id=131472712",
        "imgUrl": null,
        "contentType": "news",
        "breakingLabel": null,
        "breakingHeadline": null,
        "breakingUrl": null,
        "slotKey": "5be6806db8a5"
      },
      "last": {
        "runId": "abc_2026-03-28T19-03-18-062Z",
        "ok": true,
        "error": null,
        "fetchedAt": "2026-03-28T19:03:25.337Z",
        "shot": {
          "object_path": "screenshots/abc1/2026/03/28/abc_2026-03-28T19-03-18-062Z.jpg",
          "shot_url": null
        }
      },
      "history": [],
      "archive": [
        {
          "runId": "abc_2026-03-28T19-03-18-062Z",
          "html": "/archive/abc_2026-03-28T19-03-18-062Z.html",
          "json": "/archive/abc_2026-03-28T19-03-18-062Z.json"
        }
      ]
    },
    "cbs1": {
      "id": "cbs1",
      "name": "CBS News",
      "home_url": "https://www.cbsnews.com/",
      "kind": "hero",
      "created_at": "2026-03-28T19:03:14.326Z",
      "updated_at": "2026-03-28T19:03:33.058Z",
      "ok": true,
      "stale": false,
      "item": {
        "title": "Houthis enter Iran war, more U.S. troops arrive to Middle East",
        "url": "https://cbsnews.com/live-updates/iran-war-trump-strait-of-hormuz-oil-tanker-israel",
        "imgUrl": null,
        "slotKey": "4d6f70f0b663",
        "contentType": "live"
      },
      "last": {
        "runId": "cbs_2026-03-28T19-03-25-991Z",
        "ok": true,
        "error": null,
        "fetchedAt": "2026-03-28T19:03:33.058Z",
        "shot": {
          "object_path": "screenshots/cbs1/2026/03/28/cbs_2026-03-28T19-03-25-991Z.jpg",
          "shot_url": null
        }
      },
      "history": [],
      "archive": [
        {
          "runId": "cbs_2026-03-28T19-03-25-991Z",
          "html": "/archive/cbs_2026-03-28T19-03-25-991Z.html",
          "json": "/archive/cbs_2026-03-28T19-03-25-991Z.json"
        }
      ]
    },
    "usat1": {
      "id": "usat1",
      "name": "USA Today",
      "home_url": "https://www.usatoday.com/",
      "kind": "hero",
      "created_at": "2026-03-28T19:03:14.326Z",
      "updated_at": "2026-03-28T19:03:43.043Z",
      "ok": true,
      "stale": false,
      "item": {
        "title": "'No Kings' rallies held across US: Flagship Minnesota rally begins",
        "url": "https://usatoday.com/live-story/news/nation/2026/03/28/no-kings-protest-live-updates/89186293007",
        "imgUrl": "https://usatoday.com/gcdn/authoring/authoring-images/2026/03/28/PIND/89365036007-mp-no-kings-3-027.JPG?auto=webp&crop=2999%2C1687%2Cx0%2Cy100&format=pjpg&height=242&width=430",
        "imgAlt": null,
        "dek": "More than 3,000 \"No Kings\" events are expected throughout the nation. Protesters also gathered at a flagship rally in Saint Paul, Minnesota.",
        "breakingLabel": null,
        "breakingHeadline": null,
        "breakingUrl": null,
        "slotKey": "2f4f5e88af94",
        "contentType": "live"
      },
      "last": {
        "runId": "usat1_2026-03-28T19-03-33-630Z",
        "ok": true,
        "error": null,
        "fetchedAt": "2026-03-28T19:03:43.043Z",
        "shot": {
          "object_path": "screenshots/usat1/2026/03/28/usat1_2026-03-28T19-03-33-630Z.jpg",
          "shot_url": null
        }
      },
      "history": [],
      "archive": [
        {
          "runId": "usat1_2026-03-28T19-03-33-630Z",
          "html": "/archive/usat1_2026-03-28T19-03-33-630Z.html",
          "json": "/archive/usat1_2026-03-28T19-03-33-630Z.json"
        }
      ]
    },
    "nbc1": {
      "id": "nbc1",
      "name": "NBC News",
      "home_url": "https://www.nbcnews.com/",
      "kind": "hero",
      "created_at": "2026-03-28T19:03:14.326Z",
      "updated_at": "2026-03-28T19:03:49.267Z",
      "ok": true,
      "stale": false,
      "item": {
        "title": "No end to war in sight after one month as Iran squeezes global economy",
        "url": "https://nbcnews.com/world/iran/one-month-iran-squeezes-global-economy-rcna265279",
        "imgUrl": null,
        "breakingLabel": null,
        "breakingHeadline": null,
        "breakingUrl": null,
        "slotKey": "579270cafa55",
        "contentType": "news"
      },
      "last": {
        "runId": "nbc_2026-03-28T19-03-43-668Z",
        "ok": true,
        "error": null,
        "fetchedAt": "2026-03-28T19:03:49.267Z",
        "shot": {
          "object_path": "screenshots/nbc1/2026/03/28/nbc_2026-03-28T19-03-43-668Z.jpg",
          "shot_url": null
        }
      },
      "history": [],
      "archive": [
        {
          "runId": "nbc_2026-03-28T19-03-43-668Z",
          "html": "/archive/nbc_2026-03-28T19-03-43-668Z.html",
          "json": "/archive/nbc_2026-03-28T19-03-43-668Z.json"
        }
      ]
    },
    "cnn1": {
      "id": "cnn1",
      "name": "CNN",
      "home_url": "https://www.cnn.com/",
      "kind": "hero",
      "created_at": "2026-03-28T19:03:14.326Z",
      "updated_at": "2026-03-28T19:03:56.635Z",
      "ok": true,
      "stale": false,
      "item": {
        "title": "'No Kings' protesters stage third round of demonstrations across US Show all",
        "url": "https://cnn.com/2026/03/28/us/live-news/no-kings-protests-03-28-26",
        "imgUrl": null,
        "slotKey": "e75971db9693",
        "contentType": "live"
      },
      "last": {
        "runId": "cnn1_2026-03-28T19-03-49-664Z",
        "ok": true,
        "error": null,
        "fetchedAt": "2026-03-28T19:03:56.635Z",
        "shot": {
          "object_path": "screenshots/cnn1/2026/03/28/cnn1_2026-03-28T19-03-49-664Z.jpg",
          "shot_url": null
        }
      },
      "history": [],
      "archive": [
        {
          "runId": "cnn1_2026-03-28T19-03-49-664Z",
          "html": "/archive/cnn1_2026-03-28T19-03-49-664Z.html",
          "json": "/archive/cnn1_2026-03-28T19-03-49-664Z.json"
        }
      ]
    },
    "guardian1": {
      "id": "guardian1",
      "name": "The Guardian",
      "home_url": "https://www.theguardian.com/",
      "kind": "hero",
      "created_at": "2026-03-28T19:03:14.326Z",
      "updated_at": "2026-03-28T19:04:02.488Z",
      "ok": true,
      "stale": false,
      "item": {
        "title": "Houthi forces enter Iran conflict with missile attacks on Israeli military sites",
        "url": "https://theguardian.com/world/2026/mar/28/houthi-forces-enter-iran-conflict-with-missile-attacks-on-israeli-military-sites",
        "imgUrl": null,
        "slotKey": "b80da2377db9",
        "contentType": "news"
      },
      "last": {
        "runId": "guardian1_2026-03-28T19-03-57-115Z",
        "ok": true,
        "error": null,
        "fetchedAt": "2026-03-28T19:04:02.488Z",
        "shot": {
          "object_path": "screenshots/guardian1/2026/03/28/guardian1_2026-03-28T19-03-57-115Z.jpg",
          "shot_url": null
        }
      },
      "history": [],
      "archive": [
        {
          "runId": "guardian1_2026-03-28T19-03-57-115Z",
          "html": "/archive/guardian1_2026-03-28T19-03-57-115Z.html",
          "json": "/archive/guardian1_2026-03-28T19-03-57-115Z.json"
        }
      ]
    },
    "ap1": {
      "id": "ap1",
      "name": "Associated Press",
      "home_url": "https://apnews.com/",
      "kind": "hero",
      "created_at": "2026-03-28T19:03:14.326Z",
      "updated_at": "2026-03-28T19:04:10.551Z",
      "ok": true,
      "stale": false,
      "item": {
        "title": "Trump’s conflicting messages sow confusion over the Iran war",
        "url": "https://apnews.com/article/trump-iran-war-conflicting-messages-f9269cc4fe1cee914501b68ec5b6c217",
        "imgUrl": null,
        "slotKey": "083847305a8b",
        "contentType": "news"
      },
      "last": {
        "runId": "ap1_2026-03-28T19-04-02-931Z",
        "ok": true,
        "error": null,
        "fetchedAt": "2026-03-28T19:04:10.551Z",
        "shot": {
          "object_path": "screenshots/ap1/2026/03/28/ap1_2026-03-28T19-04-02-931Z.jpg",
          "shot_url": null
        }
      },
      "history": [],
      "archive": [
        {
          "runId": "ap1_2026-03-28T19-04-02-931Z",
          "html": "/archive/ap1_2026-03-28T19-04-02-931Z.html",
          "json": "/archive/ap1_2026-03-28T19-04-02-931Z.json"
        }
      ]
    },
    "latimes1": {
      "id": "latimes1",
      "name": "Los Angeles Times",
      "home_url": "https://www.latimes.com/",
      "kind": "hero",
      "created_at": "2026-03-28T19:03:14.326Z",
      "updated_at": "2026-03-28T19:04:18.638Z",
      "ok": true,
      "stale": false,
      "item": {
        "title": "Large protests expected against Trump amid war in Iran",
        "url": "https://latimes.com/california/live/no-kings-protests-live-updates-southern-california",
        "imgUrl": null,
        "slotKey": "06617b56ef8d",
        "contentType": "live"
      },
      "last": {
        "runId": "latimes1_2026-03-28T19-04-11-042Z",
        "ok": true,
        "error": null,
        "fetchedAt": "2026-03-28T19:04:18.638Z",
        "shot": {
          "object_path": "screenshots/latimes1/2026/03/28/latimes1_2026-03-28T19-04-11-042Z.jpg",
          "shot_url": null
        }
      },
      "history": [],
      "archive": [
        {
          "runId": "latimes1_2026-03-28T19-04-11-042Z",
          "html": "/archive/latimes1_2026-03-28T19-04-11-042Z.html",
          "json": "/archive/latimes1_2026-03-28T19-04-11-042Z.json"
        }
      ]
    },
    "npr1": {
      "id": "npr1",
      "name": "NPR",
      "home_url": "https://www.npr.org/",
      "kind": "hero",
      "created_at": "2026-03-28T19:03:14.326Z",
      "updated_at": "2026-03-28T19:04:28.538Z",
      "ok": true,
      "stale": false,
      "item": {
        "title": "'No Kings' aims for record turnout in Saturday's anti-Trump protests",
        "url": "https://npr.org/2026/03/28/nx-s1-5763702/no-kings-saturday-protests",
        "imgUrl": null,
        "slotKey": "3f6d722bf103",
        "contentType": "news"
      },
      "last": {
        "runId": "npr1_2026-03-28T19-04-19-053Z",
        "ok": true,
        "error": null,
        "fetchedAt": "2026-03-28T19:04:28.538Z",
        "shot": {
          "object_path": "screenshots/npr1/2026/03/28/npr1_2026-03-28T19-04-19-053Z.jpg",
          "shot_url": null
        }
      },
      "history": [],
      "archive": [
        {
          "runId": "npr1_2026-03-28T19-04-19-053Z",
          "html": "/archive/npr1_2026-03-28T19-04-19-053Z.html",
          "json": "/archive/npr1_2026-03-28T19-04-19-053Z.json"
        }
      ]
    },
    "bbc1": {
      "id": "bbc1",
      "name": "BBC",
      "home_url": "https://www.bbc.com/",
      "kind": "hero",
      "created_at": "2026-03-28T19:03:14.326Z",
      "updated_at": "2026-03-28T19:04:33.932Z",
      "ok": true,
      "stale": false,
      "item": {
        "title": "Israeli strike kills journalists in Lebanon, as Yemen says Iran 'dragging country into war'",
        "url": "https://bbc.com/news/live/cje4x38q8xqt",
        "imgUrl": null,
        "slotKey": "b890b46a9e6c",
        "contentType": "live"
      },
      "last": {
        "runId": "bbc1_2026-03-28T19-04-28-981Z",
        "ok": true,
        "error": null,
        "fetchedAt": "2026-03-28T19:04:33.932Z",
        "shot": {
          "object_path": "screenshots/bbc1/2026/03/28/bbc1_2026-03-28T19-04-28-981Z.jpg",
          "shot_url": null
        }
      },
      "history": [],
      "archive": [
        {
          "runId": "bbc1_2026-03-28T19-04-28-981Z",
          "html": "/archive/bbc1_2026-03-28T19-04-28-981Z.html",
          "json": "/archive/bbc1_2026-03-28T19-04-28-981Z.json"
        }
      ]
    },
    "fox1": {
      "id": "fox1",
      "name": "Fox News",
      "home_url": "https://www.foxnews.com/",
      "kind": "hero",
      "created_at": "2026-03-28T19:03:14.326Z",
      "updated_at": "2026-03-28T19:04:40.836Z",
      "ok": true,
      "stale": false,
      "item": {
        "title": "$3B network behind ‘No Kings’ protests tied to communist 'revolution' push, investigation finds",
        "url": "https://foxnews.com/us/500-groups-3b-revenues-behind-nokings-protests-communist-call-revolution",
        "imgUrl": null,
        "slotKey": "6b38efbc88f8",
        "contentType": "news"
      },
      "last": {
        "runId": "fox1_2026-03-28T19-04-34-409Z",
        "ok": true,
        "error": null,
        "fetchedAt": "2026-03-28T19:04:40.836Z",
        "shot": {
          "object_path": "screenshots/fox1/2026/03/28/fox1_2026-03-28T19-04-34-409Z.jpg",
          "shot_url": null
        }
      },
      "history": [],
      "archive": [
        {
          "runId": "fox1_2026-03-28T19-04-34-409Z",
          "html": "/archive/fox1_2026-03-28T19-04-34-409Z.html",
          "json": "/archive/fox1_2026-03-28T19-04-34-409Z.json"
        }
      ]
    },
    "yahoo1": {
      "id": "yahoo1",
      "name": "Yahoo News",
      "home_url": "https://news.yahoo.com/",
      "kind": "hero",
      "created_at": "2026-03-28T19:03:14.326Z",
      "updated_at": "2026-03-28T19:04:55.069Z",
      "ok": true,
      "stale": false,
      "item": {
        "title": "New testimony reveals where Epstein hard drives went after FBI raid",
        "url": "https://news.yahoo.com/articles/diamonds-hard-drives-jeffrey-epsteins-100101578.html",
        "imgUrl": null,
        "slotKey": "c41bbb14e91d",
        "contentType": "news"
      },
      "last": {
        "runId": "yahoo1_2026-03-28T19-04-41-300Z",
        "ok": true,
        "error": null,
        "fetchedAt": "2026-03-28T19:04:55.069Z",
        "shot": {
          "object_path": "screenshots/yahoo1/2026/03/28/yahoo1_2026-03-28T19-04-41-300Z.jpg",
          "shot_url": null
        }
      },
      "history": [],
      "archive": [
        {
          "runId": "yahoo1_2026-03-28T19-04-41-300Z",
          "html": "/archive/yahoo1_2026-03-28T19-04-41-300Z.html",
          "json": "/archive/yahoo1_2026-03-28T19-04-41-300Z.json"
        }
      ]
    }
  }
}