{
  "sources": {
    "abc1": {
      "id": "abc1",
      "name": "ABC News",
      "home_url": "https://abcnews.com/",
      "kind": "hero",
      "created_at": "2026-05-02T19:58:54.394Z",
      "updated_at": "2026-05-02T19:59:03.045Z",
      "ok": true,
      "stale": false,
      "item": {
        "title": "Airlines reduce, cap fares for Spirit travelers looking to rebook canceled flights",
        "url": "https://abcnews.com/Business/airlines-reduce-cap-fares-spirit-travelers-rebook-cancelled/story?id=132598089",
        "imgUrl": null,
        "contentType": "news",
        "breakingLabel": null,
        "breakingHeadline": null,
        "breakingUrl": null,
        "slotKey": "5be6806db8a5"
      },
      "last": {
        "runId": "abc_2026-05-02T19-58-55-755Z",
        "ok": true,
        "error": null,
        "fetchedAt": "2026-05-02T19:59:03.045Z",
        "shot": {
          "object_path": "screenshots/abc1/2026/05/02/abc_2026-05-02T19-58-55-755Z.jpg",
          "shot_url": null
        }
      },
      "history": [],
      "archive": [
        {
          "runId": "abc_2026-05-02T19-58-55-755Z",
          "html": "/archive/abc_2026-05-02T19-58-55-755Z.html",
          "json": "/archive/abc_2026-05-02T19-58-55-755Z.json"
        }
      ]
    },
    "cbs1": {
      "id": "cbs1",
      "name": "CBS News",
      "home_url": "https://www.cbsnews.com/",
      "kind": "hero",
      "created_at": "2026-05-02T19:58:54.394Z",
      "updated_at": "2026-05-02T19:59:08.944Z",
      "ok": true,
      "stale": false,
      "item": {
        "title": "Spirit Airlines shutting down after failed effort at government rescue deal",
        "url": "https://cbsnews.com/news/spirit-airlines-shutting-down-failed-rescue-deal",
        "imgUrl": null,
        "slotKey": "4d6f70f0b663",
        "contentType": "news"
      },
      "last": {
        "runId": "cbs_2026-05-02T19-59-04-084Z",
        "ok": true,
        "error": null,
        "fetchedAt": "2026-05-02T19:59:08.944Z",
        "shot": {
          "object_path": "screenshots/cbs1/2026/05/02/cbs_2026-05-02T19-59-04-084Z.jpg",
          "shot_url": null
        }
      },
      "history": [],
      "archive": [
        {
          "runId": "cbs_2026-05-02T19-59-04-084Z",
          "html": "/archive/cbs_2026-05-02T19-59-04-084Z.html",
          "json": "/archive/cbs_2026-05-02T19-59-04-084Z.json"
        }
      ]
    },
    "usat1": {
      "id": "usat1",
      "name": "USA Today",
      "home_url": "https://www.usatoday.com/",
      "kind": "hero",
      "created_at": "2026-05-02T19:58:54.394Z",
      "updated_at": "2026-05-02T19:59:17.355Z",
      "ok": true,
      "stale": false,
      "item": {
        "title": "Kentucky Derby odds for each horse in the Churchill Downs field",
        "url": "https://usatoday.com/story/sports/horses/triple/derby/2026/05/01/kentucky-derby-field-odds-horses-latest/89875797007",
        "imgUrl": "https://usatoday.com/gcdn/authoring/authoring-images/2026/05/02/USAT/89907793007-usatsi-28840681-168402559-lowres.jpg?auto=webp&crop=2441%2C1373%2Cx0%2Cy0&format=pjpg&height=242&width=430",
        "imgAlt": null,
        "dek": "A total of 20 horses will compete in the 152nd Kentucky Derby in 2026. Here is the list of participants and their latest odds to win.",
        "breakingLabel": null,
        "breakingHeadline": null,
        "breakingUrl": null,
        "slotKey": "2f4f5e88af94",
        "contentType": "news"
      },
      "last": {
        "runId": "usat1_2026-05-02T19-59-09-670Z",
        "ok": true,
        "error": null,
        "fetchedAt": "2026-05-02T19:59:17.355Z",
        "shot": {
          "object_path": "screenshots/usat1/2026/05/02/usat1_2026-05-02T19-59-09-670Z.jpg",
          "shot_url": null
        }
      },
      "history": [],
      "archive": [
        {
          "runId": "usat1_2026-05-02T19-59-09-670Z",
          "html": "/archive/usat1_2026-05-02T19-59-09-670Z.html",
          "json": "/archive/usat1_2026-05-02T19-59-09-670Z.json"
        }
      ]
    },
    "nbc1": {
      "id": "nbc1",
      "name": "NBC News",
      "home_url": "https://www.nbcnews.com/",
      "kind": "hero",
      "created_at": "2026-05-02T19:58:54.394Z",
      "updated_at": "2026-05-02T19:59:24.813Z",
      "ok": true,
      "stale": false,
      "item": {
        "title": "Spirit Airlines is closing down. Thousands of employees and travelers are impacted.",
        "url": "https://nbcnews.com/business/consumer/spirit-airlines-shuts-down-rcna343155",
        "imgUrl": null,
        "breakingLabel": null,
        "breakingHeadline": null,
        "breakingUrl": null,
        "slotKey": "579270cafa55",
        "contentType": "news"
      },
      "last": {
        "runId": "nbc_2026-05-02T19-59-18-468Z",
        "ok": true,
        "error": null,
        "fetchedAt": "2026-05-02T19:59:24.813Z",
        "shot": {
          "object_path": "screenshots/nbc1/2026/05/02/nbc_2026-05-02T19-59-18-468Z.jpg",
          "shot_url": null
        }
      },
      "history": [],
      "archive": [
        {
          "runId": "nbc_2026-05-02T19-59-18-468Z",
          "html": "/archive/nbc_2026-05-02T19-59-18-468Z.html",
          "json": "/archive/nbc_2026-05-02T19-59-18-468Z.json"
        }
      ]
    },
    "cnn1": {
      "id": "cnn1",
      "name": "CNN",
      "home_url": "https://www.cnn.com/",
      "kind": "hero",
      "created_at": "2026-05-02T19:58:54.394Z",
      "updated_at": "2026-05-02T19:59:32.369Z",
      "ok": true,
      "stale": false,
      "item": {
        "title": "Spirit shut down leaves passengers stranded Show all",
        "url": "https://cnn.com/2026/05/02/us/travel-disruption-spirit-airlines",
        "imgUrl": null,
        "slotKey": "e75971db9693",
        "contentType": "news"
      },
      "last": {
        "runId": "cnn1_2026-05-02T19-59-25-344Z",
        "ok": true,
        "error": null,
        "fetchedAt": "2026-05-02T19:59:32.369Z",
        "shot": {
          "object_path": "screenshots/cnn1/2026/05/02/cnn1_2026-05-02T19-59-25-344Z.jpg",
          "shot_url": null
        }
      },
      "history": [],
      "archive": [
        {
          "runId": "cnn1_2026-05-02T19-59-25-344Z",
          "html": "/archive/cnn1_2026-05-02T19-59-25-344Z.html",
          "json": "/archive/cnn1_2026-05-02T19-59-25-344Z.json"
        }
      ]
    },
    "guardian1": {
      "id": "guardian1",
      "name": "The Guardian",
      "home_url": "https://www.theguardian.com/",
      "kind": "hero",
      "created_at": "2026-05-02T19:58:54.394Z",
      "updated_at": "2026-05-02T19:59:38.062Z",
      "ok": true,
      "stale": false,
      "item": {
        "title": "ICE hires firm accused of ‘torture’ to track down undocumented children",
        "url": "https://theguardian.com/us-news/2026/may/02/ice-contracter-torture-allegations-undocumented-children",
        "imgUrl": null,
        "slotKey": "b80da2377db9",
        "contentType": "news"
      },
      "last": {
        "runId": "guardian1_2026-05-02T19-59-33-045Z",
        "ok": true,
        "error": null,
        "fetchedAt": "2026-05-02T19:59:38.062Z",
        "shot": {
          "object_path": "screenshots/guardian1/2026/05/02/guardian1_2026-05-02T19-59-33-045Z.jpg",
          "shot_url": null
        }
      },
      "history": [],
      "archive": [
        {
          "runId": "guardian1_2026-05-02T19-59-33-045Z",
          "html": "/archive/guardian1_2026-05-02T19-59-33-045Z.html",
          "json": "/archive/guardian1_2026-05-02T19-59-33-045Z.json"
        }
      ]
    },
    "ap1": {
      "id": "ap1",
      "name": "Associated Press",
      "home_url": "https://apnews.com/",
      "kind": "hero",
      "created_at": "2026-05-02T19:58:54.394Z",
      "updated_at": "2026-05-02T19:59:55.025Z",
      "ok": true,
      "stale": false,
      "item": {
        "title": "Trump flouts lower court rulings in unprecedented display of executive power",
        "url": "https://apnews.com/article/trump-courts-contempt-defiance-7b94b24901d42961afe323d02e352733",
        "imgUrl": null,
        "slotKey": "083847305a8b",
        "contentType": "news"
      },
      "last": {
        "runId": "ap1_2026-05-02T19-59-38-622Z",
        "ok": true,
        "error": null,
        "fetchedAt": "2026-05-02T19:59:55.025Z",
        "shot": {
          "object_path": "screenshots/ap1/2026/05/02/ap1_2026-05-02T19-59-38-622Z.jpg",
          "shot_url": null
        }
      },
      "history": [],
      "archive": [
        {
          "runId": "ap1_2026-05-02T19-59-38-622Z",
          "html": "/archive/ap1_2026-05-02T19-59-38-622Z.html",
          "json": "/archive/ap1_2026-05-02T19-59-38-622Z.json"
        }
      ]
    },
    "latimes1": {
      "id": "latimes1",
      "name": "Los Angeles Times",
      "home_url": "https://www.latimes.com/",
      "kind": "hero",
      "created_at": "2026-05-02T19:58:54.394Z",
      "updated_at": "2026-05-02T20:00:06.491Z",
      "ok": true,
      "stale": false,
      "item": {
        "title": "California, Arizona and Nevada announce new water-saving plan for dwindling Colorado River",
        "url": "https://latimes.com/environment/story/2026-05-02/california-new-colorado-river-plan",
        "imgUrl": null,
        "slotKey": "06617b56ef8d",
        "contentType": "news"
      },
      "last": {
        "runId": "latimes1_2026-05-02T19-59-55-848Z",
        "ok": true,
        "error": null,
        "fetchedAt": "2026-05-02T20:00:06.491Z",
        "shot": {
          "object_path": "screenshots/latimes1/2026/05/02/latimes1_2026-05-02T19-59-55-848Z.jpg",
          "shot_url": null
        }
      },
      "history": [],
      "archive": [
        {
          "runId": "latimes1_2026-05-02T19-59-55-848Z",
          "html": "/archive/latimes1_2026-05-02T19-59-55-848Z.html",
          "json": "/archive/latimes1_2026-05-02T19-59-55-848Z.json"
        }
      ]
    },
    "npr1": {
      "id": "npr1",
      "name": "NPR",
      "home_url": "https://www.npr.org/",
      "kind": "hero",
      "created_at": "2026-05-02T19:58:54.394Z",
      "updated_at": "2026-05-02T20:00:15.551Z",
      "ok": true,
      "stale": false,
      "item": {
        "title": "Can Trump's latest pick for surgeon general make it through confirmation?",
        "url": "https://npr.org/2026/05/02/nx-s1-5808313/nicole-saphier-surgeon-general-trump-confirmation",
        "imgUrl": null,
        "slotKey": "3f6d722bf103",
        "contentType": "news"
      },
      "last": {
        "runId": "npr1_2026-05-02T20-00-07-216Z",
        "ok": true,
        "error": null,
        "fetchedAt": "2026-05-02T20:00:15.551Z",
        "shot": {
          "object_path": "screenshots/npr1/2026/05/02/npr1_2026-05-02T20-00-07-216Z.jpg",
          "shot_url": null
        }
      },
      "history": [],
      "archive": [
        {
          "runId": "npr1_2026-05-02T20-00-07-216Z",
          "html": "/archive/npr1_2026-05-02T20-00-07-216Z.html",
          "json": "/archive/npr1_2026-05-02T20-00-07-216Z.json"
        }
      ]
    },
    "bbc1": {
      "id": "bbc1",
      "name": "BBC",
      "home_url": "https://www.bbc.com/",
      "kind": "hero",
      "created_at": "2026-05-02T19:58:54.394Z",
      "updated_at": "2026-05-02T20:00:21.111Z",
      "ok": true,
      "stale": false,
      "item": {
        "title": "Germany says US troop withdrawal 'foreseeable' as Nato seeks clarification",
        "url": "https://bbc.com/news/articles/cd9pn541jjlo",
        "imgUrl": null,
        "slotKey": "b890b46a9e6c",
        "contentType": "news"
      },
      "last": {
        "runId": "bbc1_2026-05-02T20-00-16-366Z",
        "ok": true,
        "error": null,
        "fetchedAt": "2026-05-02T20:00:21.111Z",
        "shot": {
          "object_path": "screenshots/bbc1/2026/05/02/bbc1_2026-05-02T20-00-16-366Z.jpg",
          "shot_url": null
        }
      },
      "history": [],
      "archive": [
        {
          "runId": "bbc1_2026-05-02T20-00-16-366Z",
          "html": "/archive/bbc1_2026-05-02T20-00-16-366Z.html",
          "json": "/archive/bbc1_2026-05-02T20-00-16-366Z.json"
        }
      ]
    },
    "fox1": {
      "id": "fox1",
      "name": "Fox News",
      "home_url": "https://www.foxnews.com/",
      "kind": "hero",
      "created_at": "2026-05-02T19:58:54.394Z",
      "updated_at": "2026-05-02T20:00:26.835Z",
      "ok": true,
      "stale": false,
      "item": {
        "title": "NATO partner's blunt reaction to US troop exit as Trump's feud with chancellor escalates",
        "url": "https://foxnews.com/live-news/iran-war-trump-blockade-strait-hormuz-oil-prices-may-2",
        "imgUrl": null,
        "slotKey": "6b38efbc88f8",
        "contentType": "live"
      },
      "last": {
        "runId": "fox1_2026-05-02T20-00-21-607Z",
        "ok": true,
        "error": null,
        "fetchedAt": "2026-05-02T20:00:26.835Z",
        "shot": {
          "object_path": "screenshots/fox1/2026/05/02/fox1_2026-05-02T20-00-21-607Z.jpg",
          "shot_url": null
        }
      },
      "history": [],
      "archive": [
        {
          "runId": "fox1_2026-05-02T20-00-21-607Z",
          "html": "/archive/fox1_2026-05-02T20-00-21-607Z.html",
          "json": "/archive/fox1_2026-05-02T20-00-21-607Z.json"
        }
      ]
    },
    "yahoo1": {
      "id": "yahoo1",
      "name": "Yahoo News",
      "home_url": "https://news.yahoo.com/",
      "kind": "hero",
      "created_at": "2026-05-02T19:58:54.394Z",
      "updated_at": "2026-05-02T20:00:35.335Z",
      "ok": true,
      "stale": false,
      "item": {
        "title": "Video analysis raises new questions about White House press dinner shooting",
        "url": "https://news.yahoo.com/news/articles/first-cnn-judge-privately-admonishes-175100444.html",
        "imgUrl": null,
        "slotKey": "c41bbb14e91d",
        "contentType": "news"
      },
      "last": {
        "runId": "yahoo1_2026-05-02T20-00-27-636Z",
        "ok": true,
        "error": null,
        "fetchedAt": "2026-05-02T20:00:35.335Z",
        "shot": {
          "object_path": "screenshots/yahoo1/2026/05/02/yahoo1_2026-05-02T20-00-27-636Z.jpg",
          "shot_url": null
        }
      },
      "history": [],
      "archive": [
        {
          "runId": "yahoo1_2026-05-02T20-00-27-636Z",
          "html": "/archive/yahoo1_2026-05-02T20-00-27-636Z.html",
          "json": "/archive/yahoo1_2026-05-02T20-00-27-636Z.json"
        }
      ]
    }
  }
}