{
  "ok": true,
  "generatedAt": "2026-02-13T16:36:07.586Z",
  "sources": {
    "abc1": {
      "ok": true,
      "updatedAt": "2026-02-13T16:36:14.937Z",
      "error": null,
      "runId": "abc_2026-02-13T16-36-07-703Z",
      "since": "2026-02-13T15:55:05.988Z",
      "item": {
        "title": "Nancy Guthrie kidnapping suspect: What we know",
        "url": "https://abcnews.com/US/nancy-guthrie-kidnapping-suspect/story?id=130133800",
        "imgUrl": null,
        "slotKey": "5be6806db8a5"
      }
    },
    "cbs1": {
      "ok": true,
      "updatedAt": "2026-02-13T16:36:21.105Z",
      "error": null,
      "runId": "cbs_2026-02-13T16-36-15-113Z",
      "since": "2026-02-13T15:01:54.029Z",
      "item": {
        "title": "Inflation cooled in January with prices rising at 2.4% annual pace, CPI report shows",
        "url": "https://www.cbsnews.com/news/cpi-report-today-inflation-january-2026-tariffs/",
        "imgUrl": null,
        "slotKey": "4d6f70f0b663"
      }
    },
    "usat1": {
      "ok": true,
      "updatedAt": "2026-02-13T16:36:28.273Z",
      "error": null,
      "runId": "usat1_2026-02-13T16-36-21-347Z",
      "since": "2026-02-13T15:55:05.988Z",
      "item": {
        "title": "RFK Jr. has been health secretary for a year. What has he done?",
        "url": "https://www.usatoday.com/story/life/health-wellness/2026/02/13/rfk-jr-year-as-health-secretary/88607416007/",
        "imgUrl": "https://www.usatoday.com/gcdn/authoring/authoring-images/2025/03/03/USAT/81143113007-usatsi-25344293.jpg?crop=3935,2215,x0,y208&width=430&height=242&format=pjpg&auto=webp",
        "imgAlt": null,
        "dek": "What has RFK Jr. done in his first year as health secretary? We took a look back at some major moments.",
        "slotKey": "2f4f5e88af94"
      }
    },
    "nbc1": {
      "ok": true,
      "updatedAt": "2026-02-13T16:36:33.625Z",
      "error": null,
      "runId": "nbc_2026-02-13T16-36-28-579Z",
      "since": "2026-02-13T15:01:54.029Z",
      "item": {
        "title": "FBI doubles reward as tips pour in",
        "url": "https://www.nbcnews.com/news/us-news/live-blog/live-updates-nancy-guthrie-savannah-search-rcna258861",
        "imgUrl": null,
        "slotKey": "579270cafa55"
      }
    },
    "cnn1": {
      "ok": true,
      "updatedAt": "2026-02-13T16:36:40.531Z",
      "error": null,
      "runId": "cnn1_2026-02-13T16-36-33-777Z",
      "since": "2026-02-13T16:36:07.586Z",
      "item": {
        "title": "Two top RFK Jr. aides, including interim CDC director, to leave HHS",
        "url": "https://www.cnn.com/2026/02/13/health/rfk-aides-jim-oneill-hhs-cdc",
        "imgUrl": null,
        "slotKey": "e75971db9693"
      }
    },
    "reuters1": {
      "ok": true,
      "updatedAt": "2026-02-13T16:36:44.651Z",
      "error": null,
      "runId": "reuters1_2026-02-13T16-36-40-679Z",
      "since": "2026-02-13T07:59:33.973Z",
      "item": {
        "title": "Charts show how Trump is isolating the US on world stage",
        "url": "https://www.theguardian.com/world/ng-interactive/2026/feb/13/these-charts-show-how-trump-is-isolating-the-us-on-the-world-stage",
        "imgUrl": null,
        "slotKey": "4c3ef987876a"
      }
    },
    "ap1": {
      "ok": true,
      "updatedAt": "2026-02-13T16:36:51.305Z",
      "error": null,
      "runId": "ap1_2026-02-13T16-36-44-792Z",
      "since": "2026-02-13T16:36:07.586Z",
      "item": {
        "title": "What to know about the Homeland Security shutdown starting this weekend",
        "url": "https://apnews.com/article/homeland-security-shutdown-ice-funding-7bf62bc50ca0a6a6013a714bee2ffdb4",
        "imgUrl": null,
        "slotKey": "083847305a8b"
      }
    },
    "latimes1": {
      "ok": true,
      "updatedAt": "2026-02-13T16:37:00.496Z",
      "error": null,
      "runId": "latimes1_2026-02-13T16-36-51-486Z",
      "since": "2026-02-13T13:22:29.778Z",
      "item": {
        "title": "Cedars-Sinai didn’t act on four decades of complaints about gynecologist’s sexual abuse, lawsuits allege",
        "url": "https://www.latimes.com/science/story/2026-02-13/cedars-sinai-didnt-act-on-years-of-abuse-complaints-lawsuits-say",
        "imgUrl": null,
        "slotKey": "06617b56ef8d"
      }
    },
    "npr1": {
      "ok": true,
      "updatedAt": "2026-02-13T16:37:11.129Z",
      "error": null,
      "runId": "npr1_2026-02-13T16-37-00-678Z",
      "since": "2026-02-13T15:01:54.029Z",
      "item": {
        "title": "RFK Jr. made promises to get his job as health secretary. He's broken many of them",
        "url": "https://www.npr.org/2026/02/13/nx-s1-5712721/rfk-jr-children-vaccines-cdc-funding-autism-immunizations",
        "imgUrl": null,
        "slotKey": "3f6d722bf103"
      }
    }
  }
}