{
  "ok": true,
  "generatedAt": "2026-03-16T12:00:05.698Z",
  "sources": {
    "abc1": {
      "ok": true,
      "updatedAt": "2026-03-16T12:00:12.615Z",
      "error": null,
      "runId": "abc_2026-03-16T12-00-05-810Z",
      "since": "2026-03-16T03:32:15.290Z",
      "item": {
        "title": "Oscars 2026: Full winners list from the 98th Academy Awards",
        "url": "https://abcnews.com/GMA/Culture/oscars-2026-full-winners-list/story?id=130769299",
        "imgUrl": null,
        "contentType": "news",
        "breakingLabel": null,
        "breakingHeadline": null,
        "breakingUrl": null,
        "slotKey": "5be6806db8a5"
      }
    },
    "cbs1": {
      "ok": true,
      "updatedAt": "2026-03-16T12:00:24.500Z",
      "error": null,
      "runId": "cbs_2026-03-16T12-00-15-666Z",
      "since": "2026-03-16T11:14:40.840Z",
      "item": {
        "title": "Iran war keeps Strait of Hormuz paralyzed and oil prices over $100",
        "url": "https://cbsnews.com/live-updates/iran-war-oil-prices-strait-of-hormuz-trump-threat-kharg-island",
        "imgUrl": null,
        "slotKey": "4d6f70f0b663",
        "contentType": "live"
      }
    },
    "usat1": {
      "ok": true,
      "updatedAt": "2026-03-16T12:00:33.412Z",
      "error": null,
      "runId": "usat1_2026-03-16T12-00-24-754Z",
      "since": "2026-03-16T05:31:43.428Z",
      "item": {
        "title": "The best (and worst) Oscar moments, from Conan to 'Sinners'",
        "url": "https://usatoday.com/story/entertainment/movies/2026/03/15/oscars-2026-highlights-best-worst-moments/89170194007",
        "imgUrl": "https://usatoday.com/gcdn/authoring/authoring-images/2026/03/16/USAT/89175825007-2266326804.jpg?auto=webp&crop=3959%2C2227%2Cx0%2Cy0&format=pjpg&height=242&width=430",
        "imgAlt": null,
        "dek": "You won't believe what happened at the 98th Academy Awards. From Michael B. Jordan to Amy Madigan, here are the night's most discussed moments.",
        "breakingLabel": "Breaking News",
        "breakingHeadline": "Rachel Goldberg-Polin endured a parent's worst nightmare. Now, the USA TODAY Women of the Year honoree is teaching the world empathy.",
        "breakingUrl": "https://usatoday.com/story/news/world/2026/03/02/rachel-goldberg-polin-women-of-the-year-2026/88655164007",
        "slotKey": "2f4f5e88af94",
        "contentType": "news"
      }
    },
    "nbc1": {
      "ok": true,
      "updatedAt": "2026-03-16T12:00:39.195Z",
      "error": null,
      "runId": "nbc_2026-03-16T12-00-33-722Z",
      "since": "2026-03-16T12:00:05.698Z",
      "item": {
        "title": "Cuba will allow nationals abroad to invest in and own businesses on the island, economic czar says",
        "url": "https://nbcnews.com/world/cuba/cuba-allow-nationals-living-abroad-invest-businesses-island-economy-rcna263637",
        "imgUrl": null,
        "breakingLabel": "Breaking News",
        "breakingHeadline": "Morning Rundown: Oscars takeaways, the race to reopen the Strait of Hormuz, and voters' changing views on Israel",
        "breakingUrl": "https://nbcnews.com/news/us-news/recapping-academy-awards-strait-hormuz-morning-rundown-rcna263536",
        "slotKey": "579270cafa55",
        "contentType": "news"
      }
    },
    "cnn1": {
      "ok": true,
      "updatedAt": "2026-03-16T12:00:47.901Z",
      "error": null,
      "runId": "cnn1_2026-03-16T12-00-39-370Z",
      "since": "2026-03-16T05:31:43.428Z",
      "item": {
        "title": "Trump calls for help securing Strait of Hormuz, but no country commits Show all",
        "url": "https://cnn.com/world/live-news/iran-war-us-israel-trump-03-16-26",
        "imgUrl": null,
        "slotKey": "e75971db9693",
        "contentType": "live"
      }
    },
    "guardian1": {
      "ok": true,
      "updatedAt": "2026-03-16T12:00:52.556Z",
      "error": null,
      "runId": "guardian1_2026-03-16T12-00-48-080Z",
      "since": "2026-03-16T10:16:55.803Z",
      "item": {
        "title": "Trump threatens ‘very bad’ future for Nato if allies fail to help secure strait of Hormuz",
        "url": "https://theguardian.com/world/live/2026/mar/16/iran-war-live-updates-news-oil-trump-hormuz-dubai-airport-israel-targets",
        "imgUrl": null,
        "slotKey": "b80da2377db9",
        "contentType": "live"
      }
    },
    "ap1": {
      "ok": true,
      "updatedAt": "2026-03-16T12:01:04.113Z",
      "error": null,
      "runId": "ap1_2026-03-16T12-00-52-724Z",
      "since": "2026-03-16T06:55:52.352Z",
      "item": {
        "title": "Iranian strikes rain down on Gulf states as Trump demands help to keep the Strait of Hormuz open",
        "url": "https://apnews.com/live/iran-war-israel-trump-03-16-2026",
        "imgUrl": null,
        "slotKey": "083847305a8b",
        "contentType": "live"
      }
    },
    "latimes1": {
      "ok": true,
      "updatedAt": "2026-03-16T12:01:14.073Z",
      "error": null,
      "runId": "latimes1_2026-03-16T12-01-04-394Z",
      "since": "2026-03-16T12:00:05.698Z",
      "item": {
        "title": "Downtown L.A. needs retail resuscitation. San Francisco’s subsidized shops offer a solution",
        "url": "https://latimes.com/business/story/2026-03-16/downtown-la-needs-retail-resuscitation-san-franciscos-subsidized-shops-offer-solution",
        "imgUrl": null,
        "slotKey": "06617b56ef8d",
        "contentType": "news"
      }
    },
    "npr1": {
      "ok": true,
      "updatedAt": "2026-03-16T12:01:22.909Z",
      "error": null,
      "runId": "npr1_2026-03-16T12-01-14-280Z",
      "since": "2026-03-16T10:16:55.803Z",
      "item": {
        "title": "Trump threatens NATO allies over Strait of Hormuz help",
        "url": "https://npr.org/2026/03/16/nx-s1-5749109/trump-threatens-nato-strait-hormuz-iran-war",
        "imgUrl": null,
        "slotKey": "3f6d722bf103",
        "contentType": "news"
      }
    },
    "bbc1": {
      "ok": true,
      "updatedAt": "2026-03-16T12:01:27.766Z",
      "error": null,
      "runId": "bbc1_2026-03-16T12-01-23-116Z",
      "since": "2026-03-16T05:31:43.428Z",
      "item": {
        "title": "UK won't be drawn into 'wider war’ and will work with allies on Strait of Hormuz plan, Starmer says",
        "url": "https://bbc.com/news/live/cx2lr40g17kt",
        "imgUrl": null,
        "slotKey": "b890b46a9e6c",
        "contentType": "live"
      }
    },
    "fox1": {
      "ok": true,
      "updatedAt": "2026-03-16T12:01:35.807Z",
      "error": null,
      "runId": "fox1_2026-03-16T12-01-27-912Z",
      "since": "2026-03-16T11:14:40.840Z",
      "item": {
        "title": "Israel destroys 'strategic asset' of Iran's former supreme leader to disrupt regime's ally coordination",
        "url": "https://foxnews.com/live-news/us-iran-israel-war-latest-march-16",
        "imgUrl": null,
        "slotKey": "6b38efbc88f8",
        "contentType": "live"
      }
    },
    "yahoo1": {
      "ok": true,
      "updatedAt": "2026-03-16T12:01:45.926Z",
      "error": null,
      "runId": "yahoo1_2026-03-16T12-01-35-998Z",
      "since": "2026-03-16T11:14:40.840Z",
      "item": {
        "title": "Iran attacks Gulf energy targets as oil shipping disruption raises crisis fears",
        "url": "https://news.yahoo.com/articles/iran-hits-gulf-neighbors-keeps-053206583.html",
        "imgUrl": null,
        "slotKey": "c41bbb14e91d",
        "contentType": "news"
      }
    }
  }
}