{
  "ok": true,
  "generatedAt": "2026-02-12T14:16:40.273Z",
  "items": [
    {
      "source": "abc1",
      "updatedAt": "2026-02-12T14:16:43.226Z",
      "since": "2026-02-12T14:16:40.273Z",
      "title": "Rep. Jayapal accuses DOJ of 'spying' on her searches of unredacted Epstein files",
      "url": "https://abcnews.com/Politics/democratic-rep-pramila-jayapal-accuses-doj-spying-search/story?id=130085095",
      "imgUrl": null,
      "slotKey": "5be6806db8a5"
    },
    {
      "source": "cbs1",
      "updatedAt": "2026-02-12T14:16:45.684Z",
      "since": "2026-02-12T14:16:40.273Z",
      "title": "Watch Live: Minnesota officials testify at Senate hearing on immigration",
      "url": "https://www.cbsnews.com/live-updates/minnesota-immigration-ice-hearing-senate-homeland-security/",
      "imgUrl": null,
      "slotKey": "4d6f70f0b663"
    },
    {
      "source": "usat1",
      "updatedAt": "2026-02-12T14:16:48.308Z",
      "since": "2026-02-12T13:09:22.176Z",
      "title": "Why didn't Chock and Bates win Olympic gold? Judges' scores explained",
      "url": "https://www.usatoday.com/story/sports/olympics/2026/02/12/madison-chock-evan-bates-olympic-gold-judges/88639339007/",
      "imgUrl": "https://www.usatoday.com/gcdn/authoring/authoring-images/2026/02/12/USAT/88639347007-usatsi-28213350.jpg?crop=6725,3784,x0,y340&width=430&height=242&format=pjpg&auto=webp",
      "imgAlt": null,
      "dek": "Despite getting the majority of first place finishes in the free dance, Madison Chock and Evan Bates ended up falling short of winning the gold medal.",
      "slotKey": "2f4f5e88af94"
    },
    {
      "source": "nbc1",
      "updatedAt": "2026-02-12T14:16:51.250Z",
      "since": "2026-02-12T14:16:40.273Z",
      "title": "Jesse Diggins collapses in pain after securing bronze in women's 10km freestyle",
      "url": "https://www.nbcnews.com/sports/olympics/live-blog/2026-winter-olympics-live-updates-rcna256604",
      "imgUrl": null,
      "slotKey": "579270cafa55"
    },
    {
      "source": "cnn1",
      "updatedAt": "2026-02-12T14:16:56.735Z",
      "since": "2026-02-12T10:28:37.660Z",
      "title": "Investigators sift through thousands of tips in Nancy Guthrie case",
      "url": "https://www.cnn.com/us/live-news/nancy-guthrie-savannah-missing-mom-02-12-26",
      "imgUrl": null,
      "slotKey": "e75971db9693"
    },
    {
      "source": "reuters1",
      "updatedAt": "2026-02-12T14:16:59.025Z",
      "since": "2026-02-12T00:44:39.509Z",
      "title": "Border patrol chief praised federal agent who shot US citizen in Chicago",
      "url": "https://www.theguardian.com/us-news/2026/feb/11/gregory-bovino-praised-agent-shot-us-citizen-chicago",
      "imgUrl": null,
      "slotKey": "4c3ef987876a"
    },
    {
      "source": "ap1",
      "updatedAt": "2026-02-12T14:17:01.893Z",
      "since": "2026-02-12T04:53:25.665Z",
      "title": "Bondi clashes with Democrats as she struggles to turn the page on Epstein files furor",
      "url": "https://apnews.com/article/pam-bondi-house-judiciary-committee-justice-department-6d7502b80e42e9e9454264e242507bbd",
      "imgUrl": null,
      "slotKey": "083847305a8b"
    },
    {
      "source": "latimes1",
      "updatedAt": "2026-02-12T14:17:04.483Z",
      "since": "2026-02-12T13:09:22.176Z",
      "title": "UCLA professor’s emails to Epstein stir protest as academia is jolted by links to sex abuser",
      "url": "https://www.latimes.com/california/story/2026-02-12/ucla-mark-tramo-jeffrey-epstein-emails",
      "imgUrl": null,
      "slotKey": "06617b56ef8d"
    },
    {
      "source": "npr1",
      "updatedAt": "2026-02-12T14:17:08.602Z",
      "since": "2026-02-12T14:16:40.273Z",
      "title": "Watch: Top immigration officials testify before the Senate as a potential DHS shutdown looms",
      "url": "https://www.npr.org/2026/02/12/nx-s1-5707281/senate-dhs-oversight-hearing",
      "imgUrl": null,
      "slotKey": "3f6d722bf103"
    }
  ]
}